{"Name":"GIT Demo 1","Updated":"2016-09-29T17:28:48.2133632+10:00","Folders":[{"Name":"Modules","Path":"","SubFolders":[],"Items":[],"FullPath":"/Modules"},{"Name":"TestCases","Path":"","SubFolders":[{"Name":"User 1 Folder","Path":"/TestCases","SubFolders":[],"Items":[{"Name":"User 1 Test","Path":"/TestCases/User 1 Folder","ID":"-4695","LastModified":"0001-01-01T00:00:00","TrackingID":"e7724925-815f-4531-9d13-5461bc407602","FullPath":"/TestCases/User 1 Folder/User 1 Test"},{"Name":"Do some more testing","Path":"/TestCases/User 1 Folder","ID":"-4696","LastModified":"0001-01-01T00:00:00","TrackingID":"69eb517a-ac89-444a-a4c1-9504247633a7","FullPath":"/TestCases/User 1 Folder/Do some more testing"}],"FullPath":"/TestCases/User 1 Folder"},{"Name":"User 2 Folder","Path":"/TestCases","SubFolders":[],"Items":[{"Name":"User 2 Test","Path":"/TestCases/User 2 Folder","ID":"-4724","LastModified":"0001-01-01T00:00:00","TrackingID":"7b136414-9119-4f85-b2f1-b7078516c2f3","FullPath":"/TestCases/User 2 Folder/User 2 Test"}],"FullPath":"/TestCases/User 2 Folder"}],"Items":[],"FullPath":"/TestCases"},{"Name":"Execution","Path":"","SubFolders":[{"Name":"ExecutionLists","Path":"/Execution","SubFolders":[],"Items":[],"FullPath":"/Execution/ExecutionLists"},{"Name":"Exploratory Testing","Path":"/Execution","SubFolders":[],"Items":[],"FullPath":"/Execution/Exploratory Testing"}],"Items":[],"FullPath":"/Execution"},{"Name":"Issues","Path":"","SubFolders":[],"Items":[],"FullPath":"/Issues"},{"Name":"Reporting","Path":"","SubFolders":[],"Items":[],"FullPath":"/Reporting"},{"Name":"Requirements","Path":"","SubFolders":[],"Items":[],"FullPath":"/Requirements"},{"Name":"TestCaseDesign","Path":"","SubFolders":[],"Items":[],"FullPath":"/TestCaseDesign"}]}